meixmetric/__init__.py
meixmetric/calculate/__init__.py
meixmetric/calculate/calc.py
meixmetric/calculate/df_calc.py
meixmetric/exc/__init__.py
meixmetric/exc/mx_exc.py
meixmetric/utils/__init__.py
meixmetric/utils/date_util.py
meixmetric-0.0.15.dist-info/METADATA
meixmetric-0.0.15.dist-info/WHEEL
meixmetric-0.0.15.dist-info/top_level.txt
meixmetric-0.0.15.dist-info/RECORD
