Metadata-Version: 2.1
Name: meixmetric
Version: 0.0.15
Summary: metric algorithm for meix
Author: sunpeng
Author-email: 759302280@qq.com
License: UNKNOWN
Platform: UNKNOWN
